odoo/addons/prometheus_exporter/LICENSE
odoo/addons/prometheus_exporter/README.rst
odoo/addons/prometheus_exporter/__init__.py
odoo/addons/prometheus_exporter/__manifest__.py
odoo/addons/prometheus_exporter/controllers/__init__.py
odoo/addons/prometheus_exporter/controllers/prometheus_metrics.py
odoo/addons/prometheus_exporter/data/ir_metric.xml
odoo/addons/prometheus_exporter/images/screen.png
odoo/addons/prometheus_exporter/models/__init__.py
odoo/addons/prometheus_exporter/models/ir_metric.py
odoo/addons/prometheus_exporter/security/ir.model.access.csv
odoo/addons/prometheus_exporter/static/description/icon.png
odoo/addons/prometheus_exporter/static/description/index.html
odoo/addons/prometheus_exporter/tests/TEST_INSTRUCTIONS.rst
odoo/addons/prometheus_exporter/views/ir_metric.xml
odoo_addon_prometheus_exporter-18.0.1.0.0.dist-info/METADATA
odoo_addon_prometheus_exporter-18.0.1.0.0.dist-info/WHEEL
odoo_addon_prometheus_exporter-18.0.1.0.0.dist-info/top_level.txt
odoo_addon_prometheus_exporter-18.0.1.0.0.dist-info/RECORD
